api/__init__.py
api/soma_api.py
pysoma-0.0.14.dist-info/licenses/LICENSE
pysoma-0.0.14.dist-info/METADATA
pysoma-0.0.14.dist-info/WHEEL
pysoma-0.0.14.dist-info/top_level.txt
pysoma-0.0.14.dist-info/RECORD
