Metadata-Version: 2.4
Name: pysoma
Version: 0.0.14
Summary: A simple package for controlling SOMA devices
Home-page: https://github.com/ratsept/pysoma
Author: Wazombi Labs
Author-email: labs@wazombi.com
Classifier: Programming Language :: Python :: 3
Classifier: License :: OSI Approved :: MIT License
Classifier: Operating System :: OS Independent
Classifier: Topic :: Home Automation
License-File: LICENSE
Dynamic: author
Dynamic: author-email
Dynamic: classifier
Dynamic: description
Dynamic: description-content-type
Dynamic: home-page
Dynamic: license-file
Dynamic: summary
